{"meta":{"name":"UK NEWS ","id":"Root23","type":"channel","posterShape":"landscape","videos":[{"id":"Rootstream_23_0","title":"UK SD : Russia Today"},{"id":"Rootstream_23_1","title":"UK HD : BBC News"},{"id":"Rootstream_23_2","title":"UK SD : BBC News"},{"id":"Rootstream_23_3","title":"UK SD :  BBC Parliament"},{"id":"Rootstream_23_4","title":"UK SD : Bloomberg"},{"id":"Rootstream_23_5","title":"UK SD :  CNN"},{"id":"Rootstream_23_6","title":"UK SD : Al Jazeera English"},{"id":"Rootstream_23_7","title":"UK SD : Euronews"},{"id":"Rootstream_23_8","title":"UK SD : BBC World News"},{"id":"Rootstream_23_9","title":"UK SD :  Sky News"}]}}